README.txt
setup.cfg
setup.py
src/mekk/__init__.py
src/mekk.nozbe2xmind.egg-info/PKG-INFO
src/mekk.nozbe2xmind.egg-info/SOURCES.txt
src/mekk.nozbe2xmind.egg-info/dependency_links.txt
src/mekk.nozbe2xmind.egg-info/entry_points.txt
src/mekk.nozbe2xmind.egg-info/namespace_packages.txt
src/mekk.nozbe2xmind.egg-info/not-zip-safe
src/mekk.nozbe2xmind.egg-info/requires.txt
src/mekk.nozbe2xmind.egg-info/top_level.txt
src/mekk/nozbe2xmind/__init__.py
src/mekk/nozbe2xmind/context_icons.py
src/mekk/nozbe2xmind/run.py
src/mekk/nozbe2xmind/run_analysis.py
src/mekk/nozbe2xmind/xmind_reader.py
src/mekk/nozbe2xmind/xmind_writer.py