Metadata-Version: 1.0
Name: mekk.nozbe2xmind
Version: 0.4.0
Summary: Sync between Nozbe API and XMind data files.
Home-page: http://mekk.waw.pl/python/xmind
Author: Marcin Kasperski
Author-email: Marcin.Kasperski@mekk.waw.pl
License: LGPL
Keywords: xmind,Nozbe
Platform: UNKNOWN
Classifier: Programming Language :: Python
Classifier: Intended Audience :: Developers
Classifier: Topic :: Software Development :: Libraries :: Python Modules
